README.md
setup.py
bot_managers/__init__.py
bot_managers/__version__.py
bot_managers/bots_manager.py
bot_managers/client_manager.py
bot_managers/logger.py
bot_managers/settings.py
bot_managers/typing.py
bot_managers/updater.py
bot_managers/utils.py
bot_managers/voices.py
bot_managers.egg-info/PKG-INFO
bot_managers.egg-info/SOURCES.txt
bot_managers.egg-info/dependency_links.txt
bot_managers.egg-info/requires.txt
bot_managers.egg-info/top_level.txt
bot_managers/telethon/__init__.py
bot_managers/telethon/client.py
bot_managers/telethon/errors.py
bot_managers/telethon/markdown.py
bot_managers/telethon/methods.py
bot_managers/telethon/network.py